rustmaps/__init__.py
rustmaps/rustmaps.py
rustmaps.py-0.2.0.dist-info/entry_points.txt
rustmaps.py-0.2.0.dist-info/LICENSE.md
rustmaps.py-0.2.0.dist-info/WHEEL
rustmaps.py-0.2.0.dist-info/METADATA
rustmaps.py-0.2.0.dist-info/RECORD
