Metadata-Version: 2.1
Name: rustmaps.py
Version: 0.2.0
Summary: Wrapper for the rustmaps.com REST API
Home-page: https://github.com/RalphORama/rustmaps.py/
License: AGPL-3.0-or-later
Keywords: requests,api,development
Author: Ralph Drake
Author-email: pypi@ralphdrake.com
Requires-Python: >=3.8,<4.0
Classifier: Development Status :: 3 - Alpha
Classifier: Intended Audience :: Developers
Classifier: License :: OSI Approved :: GNU Affero General Public License v3 or later (AGPLv3+)
Classifier: Natural Language :: English
Classifier: Operating System :: OS Independent
Classifier: Programming Language :: Python :: 3
Classifier: Programming Language :: Python :: 3 :: Only
Classifier: Programming Language :: Python :: 3.10
Classifier: Programming Language :: Python :: 3.8
Classifier: Programming Language :: Python :: 3.9
Classifier: Topic :: Internet :: WWW/HTTP
Requires-Dist: requests (>=2.28.1,<3.0.0)
Project-URL: Repository, https://github.com/RalphORama/rustmaps.py/
